fastapi_resources/__init__.py
fastapi_resources/resources/__init__.py
fastapi_resources/resources/base_resource.py
fastapi_resources/resources/sqlalchemy/__init__.py
fastapi_resources/resources/sqlalchemy/base.py
fastapi_resources/resources/sqlalchemy/exceptions.py
fastapi_resources/resources/sqlalchemy/mixins.py
fastapi_resources/resources/sqlalchemy/paginators.py
fastapi_resources/resources/sqlalchemy/resources.py
fastapi_resources/resources/sqlalchemy/types.py
fastapi_resources/resources/types.py
fastapi_resources/routers/__init__.py
fastapi_resources/routers/base_router.py
fastapi_resources/routers/decorators.py
fastapi_resources/routers/json_api_router/__init__.py
fastapi_resources/routers/json_api_router/json_api_router.py
fastapi_resources/routers/json_api_router/types.py
fastapi_resources/types.py
fastapi_resources-0.6.1.dist-info/METADATA
fastapi_resources-0.6.1.dist-info/WHEEL
fastapi_resources-0.6.1.dist-info/RECORD
