Metadata-Version: 2.1
Name: fastapi-resources
Version: 0.6.1
Summary: 
Author: Ben Davis
Author-email: ben@bencdavis.com
Requires-Python: >=3.12,<4.0
Classifier: Programming Language :: Python :: 3
Classifier: Programming Language :: Python :: 3.12
Requires-Dist: fastapi (>=0.111.0,<0.112.0)
Requires-Dist: pydantic (>=2.0.2,<3.0.0)
Requires-Dist: sqlalchemy (>=2.0.30,<3.0.0)
